README.md
setup.py
elisa_clean/__init__.py
elisa_clean/__main__.py
elisa_clean/utils.py
elisa_clean.egg-info/PKG-INFO
elisa_clean.egg-info/SOURCES.txt
elisa_clean.egg-info/dependency_links.txt
elisa_clean.egg-info/requires.txt
elisa_clean.egg-info/top_level.txt